jeeves_deepspeech/__init__.py
jeeves_deepspeech/stt.py
jeeves_deepspeech-0.1.4.dist-info/DESCRIPTION.rst
jeeves_deepspeech-0.1.4.dist-info/METADATA
jeeves_deepspeech-0.1.4.dist-info/RECORD
jeeves_deepspeech-0.1.4.dist-info/WHEEL
jeeves_deepspeech-0.1.4.dist-info/entry_points.txt
jeeves_deepspeech-0.1.4.dist-info/metadata.json
jeeves_deepspeech-0.1.4.dist-info/top_level.txt
jeeves_deepspeech-0.1.4.dist-info/zip-safe
tests/__init__.py
tests/test_jeeves_deepspeech.py
