Metadata-Version: 2.0
Name: jeeves-deepspeech
Version: 0.1.4
Summary: DeepSpeech STT plugin for jeeves
Home-page: UNKNOWN
Author: Jon Robison
Author-email: narfman0@gmail.com
License: LICENSE
Keywords: jeeves-deepspeech
Platform: UNKNOWN
Classifier: Development Status :: 4 - Beta
Classifier: License :: OSI Approved :: GNU General Public License v3 (GPLv3)
Classifier: Operating System :: OS Independent
Classifier: Programming Language :: Python
Classifier: Topic :: Software Development :: Libraries :: Python Modules
Requires-Dist: deepspeech
Requires-Dist: jeeves-pa
